{
  "indexes": [
    {
      "collectionGroup": "agendas",
      "queryScope": "COLLECTION",
      "fields": [
        { "fieldPath": "eventId", "order": "ASCENDING" },
        { "fieldPath": "time", "order": "ASCENDING" }
      ]
    },
    {
      "collectionGroup": "users",
      "queryScope": "COLLECTION",
      "fields": [
        { "fieldPath": "role", "order": "ASCENDING" },
        { "fieldPath": "parentId", "order": "ASCENDING" }
      ]
    },
    {
      "collectionGroup": "users",
      "queryScope": "COLLECTION",
      "fields": [
        { "fieldPath": "parentId", "order": "ASCENDING" },
        { "fieldPath": "role", "order": "ASCENDING" },
        { "fieldPath": "status", "order": "ASCENDING" }
      ]
    },
    {
      "collectionGroup": "users",
      "queryScope": "COLLECTION",
      "fields": [
        { "fieldPath": "role", "order": "ASCENDING" },
        { "fieldPath": "status", "order": "ASCENDING" }
      ]
    },
    {
      "collectionGroup": "scanLogs",
      "queryScope": "COLLECTION",
      "fields": [
        { "fieldPath": "attendeeId", "order": "ASCENDING" },
        { "fieldPath": "timestamp", "order": "ASCENDING" }
      ]
    },
    {
      "collectionGroup": "questions",
      "queryScope": "COLLECTION",
      "fields": [
        { "fieldPath": "eventId", "order": "ASCENDING" },
        { "fieldPath": "createdAt", "order": "DESCENDING" }
      ]
    },
    {
      "collectionGroup": "scanLogs",
      "queryScope": "COLLECTION",
      "fields": [
        { "fieldPath": "gateId", "order": "ASCENDING" },
        { "fieldPath": "timestamp", "order": "DESCENDING" }
      ]
    },
    {
      "collectionGroup": "scanLogs",
      "queryScope": "COLLECTION",
      "fields": [
        { "fieldPath": "result", "order": "ASCENDING" },
        { "fieldPath": "timestamp", "order": "DESCENDING" }
      ]
    },
    {
      "collectionGroup": "speakers",
      "queryScope": "COLLECTION",
      "fields": [
        { "fieldPath": "eventId", "order": "ASCENDING" },
        { "fieldPath": "createdAt", "order": "DESCENDING" }
      ]
    },
    {
      "collectionGroup": "exhibitors",
      "queryScope": "COLLECTION",
      "fields": [
        { "fieldPath": "eventId", "order": "ASCENDING" },
        { "fieldPath": "createdAt", "order": "DESCENDING" }
      ]
    }
  ],
  "fieldOverrides": []
}
